README.md
setup.py
psfam/__init__.py
psfam/family.py
psfam/matrix_generator.py
psfam/pauli_organizer.py
psfam/pauli_utils.py
psfam.egg-info/PKG-INFO
psfam.egg-info/SOURCES.txt
psfam.egg-info/dependency_links.txt
psfam.egg-info/requires.txt
psfam.egg-info/top_level.txt