Metadata-Version: 2.1
Name: psfam
Version: 0.0.12
Summary: First attempt at putting psfam in a build.
Home-page: UNKNOWN
Author: Ben Reggio
Author-email: benjreggio@gmail.com
License: MIT
Platform: UNKNOWN
Classifier: Development Status :: 3 - Alpha
Classifier: Topic :: Utilities
Classifier: License :: OSI Approved :: MIT License
